azure/storage/__init__.py
azure_storage_nspkg-3.0.0.dist-info/DESCRIPTION.rst
azure_storage_nspkg-3.0.0.dist-info/METADATA
azure_storage_nspkg-3.0.0.dist-info/RECORD
azure_storage_nspkg-3.0.0.dist-info/WHEEL
azure_storage_nspkg-3.0.0.dist-info/metadata.json
azure_storage_nspkg-3.0.0.dist-info/top_level.txt
