Metadata-Version: 1.1
Name: azure-storage-nspkg
Version: 3.0.0
Summary: Microsoft Azure Storage Namespace Package [Internal]
Home-page: https://github.com/Azure/azure-storage-python
Author: Microsoft Corporation
Author-email: ascl@microsoft.com
License: MIT License
Platform: UNKNOWN
Classifier: Development Status :: 5 - Production/Stable
Classifier: Programming Language :: Python
Classifier: Programming Language :: Python :: 2
Classifier: Programming Language :: Python :: 2.7
Classifier: Programming Language :: Python :: 3
Classifier: Programming Language :: Python :: 3.3
Classifier: Programming Language :: Python :: 3.4
Classifier: Programming Language :: Python :: 3.5
Classifier: Programming Language :: Python :: 3.6
Classifier: License :: OSI Approved :: MIT License
